yololang/__init__.py
yololang/cache.py
yololang/client.py
yololang/prompts.py
yololang/yolo.py
yololang-0.2.1.dist-info/licenses/LICENSE
yololang-0.2.1.dist-info/METADATA
yololang-0.2.1.dist-info/WHEEL
yololang-0.2.1.dist-info/top_level.txt
yololang-0.2.1.dist-info/RECORD
