Metadata-Version: 2.4
Name: yololang
Version: 0.2.1
Summary: yololang - life is too short to write functions
Author: Stoyan Stoyanov
Project-URL: Homepage, https://github.com/stoyan-stoyanov/yololang
Project-URL: github, https://github.com/stoyan-stoyanov/yololang
Classifier: Programming Language :: Python :: 3
Classifier: License :: OSI Approved :: MIT License
Classifier: Operating System :: OS Independent
Requires-Python: >=3.9
License-File: LICENSE
Requires-Dist: openai==1.93.1
Dynamic: license-file
